odoo/addons/runbot_buildout/README.rst
odoo/addons/runbot_buildout/__init__.py
odoo/addons/runbot_buildout/__manifest__.py
odoo/addons/runbot_buildout/controllers/__init__.py
odoo/addons/runbot_buildout/controllers/main.py
odoo/addons/runbot_buildout/examples/buildout.cfg
odoo/addons/runbot_buildout/models/__init__.py
odoo/addons/runbot_buildout/models/runbot_branch.py
odoo/addons/runbot_buildout/models/runbot_build.py
odoo/addons/runbot_buildout/models/runbot_repo.py
odoo/addons/runbot_buildout/static/description/icon.png
odoo/addons/runbot_buildout/static/src/js/runbot_buildout.js
odoo/addons/runbot_buildout/tests/__init__.py
odoo/addons/runbot_buildout/tests/test_runbot_buildout.py
odoo/addons/runbot_buildout/views/runbot_branch.xml
odoo/addons/runbot_buildout/views/runbot_repo.xml
odoo/addons/runbot_buildout/views/templates.xml
odoo11_addon_runbot_buildout-11.0.1.0.0.dist-info/METADATA
odoo11_addon_runbot_buildout-11.0.1.0.0.dist-info/RECORD
odoo11_addon_runbot_buildout-11.0.1.0.0.dist-info/WHEEL
odoo11_addon_runbot_buildout-11.0.1.0.0.dist-info/top_level.txt
